<core:FragmentDefinition
    xmlns:core="sap.ui.core"
    xmlns:f="sap.ui.layout.form"
    xmlns="sap.m"
    xmlns:template="http://schemas.sap.com/sapui5/extension/sap.ui.core.template/1">
    <Toolbar id="sapOVPCustomParamToolbar">
        <ToolbarSpacer/>
            <Button icon="sap-icon://add"  press="addStaticParameterRow"/>
    </Toolbar>
    <Table id="sapOvpStaticParameters"
            items="{path:'/aAllStaticParameters'}" sticky="ColumnHeaders" inset="false"
            fixedLayout="false"
            visible="true">
        <columns>
            <Column id="1">
                <Text text="key"/>
            </Column>
            <Column id="2">
                <Text text="value"/>
            </Column>
            <Column>
                <Text text=""/>
            </Column>
        </columns>
        <items>
            <ColumnListItem>
                <cells>
                    <Input type="Text" value="{key}" change="updateCard" required="true" />
                    <Input type="Text" value="{value}" change="updateCard" required="true"/>
                    <Button icon="sap-icon://delete" press="onParameterDelete"/>
                </cells>
            </ColumnListItem>
        </items>
    </Table>
</core:FragmentDefinition>